{"cameraMode":{"drawMode":0,"name":"Shaded","section":"Shading Mode"},"sceneLighting":true,"audioPlay":false,"sceneViewState":{"m_AlwaysRefresh":false,"showFog":true,"showSkybox":true,"showFlares":true,"showImageEffects":true,"showParticleSystems":true,"showVisualEffectGraphs":true,"m_FxEnabled":true},"in2DMode":false,"pivot":{"x":-16.525510787963868,"y":0.7586706876754761,"z":-2.625528335571289},"rotation":{"x":-0.041450027376413348,"y":0.9443029165267944,"z":-0.1315091848373413,"w":-0.2992139756679535},"size":2.4596571922302248,"orthographic":false}